{
  "root_group": {
    "checks": [
      {
        "name": "status is 2xx",
        "path": "::status is 2xx",
        "id": "625da780c1868b693c9052f10511e6a0",
        "passes": 179138,
        "fails": 0
      }
    ],
    "name": "",
    "path": "",
    "id": "d41d8cd98f00b204e9800998ecf8427e",
    "groups": []
  },
  "options": {
    "noColor": false,
    "summaryTrendStats": [
      "avg",
      "min",
      "med",
      "max",
      "p(90)",
      "p(95)",
      "p(99)"
    ],
    "summaryTimeUnit": ""
  },
  "state": {
    "isStdOutTTY": false,
    "isStdErrTTY": false,
    "testRunDurationMs": 900933.554672
  },
  "metrics": {
    "status_2xx": {
      "values": {
        "count": 179138,
        "rate": 198.83597305377108
      },
      "type": "counter",
      "contains": "default"
    },
    "status_200": {
      "type": "counter",
      "contains": "default",
      "values": {
        "count": 179138,
        "rate": 198.83597305377108
      }
    },
    "checks": {
      "type": "rate",
      "contains": "default",
      "values": {
        "rate": 1,
        "passes": 179138,
        "fails": 0
      }
    },
    "http_req_connecting": {
      "type": "trend",
      "contains": "time",
      "values": {
        "med": 0,
        "max": 44.977863,
        "p(90)": 0,
        "p(95)": 0,
        "p(99)": 0,
        "avg": 0.008059887891525574,
        "min": 0
      }
    },
    "gs_iteration": {
      "type": "trend",
      "contains": "time",
      "values": {
        "max": 3446,
        "p(90)": 903,
        "p(95)": 953,
        "p(99)": 993,
        "avg": 502.5475722627248,
        "min": 2,
        "med": 501
      }
    },
    "http_req_tls_handshaking": {
      "values": {
        "max": 68.237405,
        "p(90)": 0,
        "p(95)": 0,
        "p(99)": 0,
        "avg": 0.0162110616392857,
        "min": 0,
        "med": 0
      },
      "type": "trend",
      "contains": "time"
    },
    "status_count": {
      "type": "counter",
      "contains": "default",
      "values": {
        "count": 179138,
        "rate": 198.83597305377108
      }
    },
    "http_req_receiving": {
      "values": {
        "min": 0.044776,
        "med": 0.206084,
        "max": 28.499019,
        "p(90)": 0.423184,
        "p(95)": 0.5426105000000001,
        "p(99)": 0.7779569999999998,
        "avg": 0.24621229896337268
      },
      "type": "trend",
      "contains": "time"
    },
    "iteration_duration": {
      "type": "trend",
      "contains": "time",
      "values": {
        "avg": 502.5640338187731,
        "min": 1.992717,
        "med": 501.0606535,
        "max": 3446.215516,
        "p(90)": 902.7900527000002,
        "p(95)": 953.0410355,
        "p(99)": 992.7983486200001
      }
    },
    "iterations": {
      "type": "counter",
      "contains": "default",
      "values": {
        "count": 179138,
        "rate": 198.83597305377108
      }
    },
    "vus_max": {
      "type": "gauge",
      "contains": "default",
      "values": {
        "value": 100,
        "min": 100,
        "max": 100
      }
    },
    "http_req_failed": {
      "type": "rate",
      "contains": "default",
      "values": {
        "passes": 0,
        "fails": 179139,
        "rate": 0
      }
    },
    "http_reqs": {
      "contains": "default",
      "values": {
        "count": 179139,
        "rate": 198.83708301353983
      },
      "type": "counter"
    },
    "gs_latency": {
      "type": "trend",
      "contains": "time",
      "values": {
        "p(95)": 3.6202028499999996,
        "p(99)": 7.363916580000018,
        "avg": 2.5070575634706476,
        "min": 1.416598,
        "med": 2.2308555,
        "max": 2773.365193,
        "p(90)": 3.0412397000000007
      },
      "thresholds": {
        "p(95)<2000": {
          "ok": true
        }
      }
    },
    "http_req_duration": {
      "type": "trend",
      "contains": "time",
      "values": {
        "p(99)": 7.367637699999983,
        "avg": 2.5071332154974897,
        "min": 1.416598,
        "med": 2.230858,
        "max": 2773.365193,
        "p(90)": 3.041272,
        "p(95)": 3.620323100000001
      },
      "thresholds": {
        "p(95)<2000": {
          "ok": true
        }
      }
    },
    "data_received": {
      "type": "counter",
      "contains": "data",
      "values": {
        "count": 5816872598,
        "rate": 6456494.5637059
      }
    },
    "gs_error_rate": {
      "type": "rate",
      "contains": "default",
      "values": {
        "rate": 0,
        "passes": 0,
        "fails": 179138
      },
      "thresholds": {
        "rate<0.05": {
          "ok": true
        }
      }
    },
    "http_req_duration{expected_response:true}": {
      "contains": "time",
      "values": {
        "p(99)": 7.367637699999983,
        "avg": 2.5071332154974897,
        "min": 1.416598,
        "med": 2.230858,
        "max": 2773.365193,
        "p(90)": 3.041272,
        "p(95)": 3.620323100000001
      },
      "type": "trend"
    },
    "data_sent": {
      "type": "counter",
      "contains": "data",
      "values": {
        "count": 40544503,
        "rate": 45002.767173835484
      }
    },
    "pages_tested": {
      "values": {
        "rate": 198.83597305377108,
        "count": 179138
      },
      "type": "counter",
      "contains": "default"
    },
    "pages_discovered": {
      "type": "counter",
      "contains": "default",
      "values": {
        "count": 37,
        "rate": 0.041068511443633014
      }
    },
    "vus": {
      "values": {
        "value": 100,
        "min": 100,
        "max": 100
      },
      "type": "gauge",
      "contains": "default"
    },
    "gs_requests": {
      "type": "counter",
      "contains": "default",
      "values": {
        "count": 179138,
        "rate": 198.83597305377108
      }
    },
    "http_req_sending": {
      "type": "trend",
      "contains": "time",
      "values": {
        "max": 0.396114,
        "p(90)": 0.066638,
        "p(95)": 0.073088,
        "p(99)": 0.09360419999999996,
        "avg": 0.05428671440054859,
        "min": 0.016084,
        "med": 0.052518
      }
    },
    "http_req_waiting": {
      "type": "trend",
      "contains": "time",
      "values": {
        "max": 2754.941308,
        "p(90)": 2.717857000000001,
        "p(95)": 3.2937760000000007,
        "p(99)": 6.920755739999976,
        "avg": 2.2066342021335434,
        "min": 1.247879,
        "med": 1.932518
      }
    },
    "http_req_blocked": {
      "type": "trend",
      "contains": "time",
      "values": {
        "p(99)": 0.000741,
        "avg": 0.025035092509150026,
        "min": 0.00011,
        "med": 0.000291,
        "max": 70.411565,
        "p(90)": 0.0004,
        "p(95)": 0.000471
      }
    }
  },
  "setup_data": {
    "urls": [
      "https://nclsbayona.github.io/p/connectivity-networking/",
      "https://nclsbayona.github.io/p/kubernetes-talos/",
      "https://nclsbayona.github.io/p/deployment-secure-webpages/",
      "https://nclsbayona.github.io/p/containers-internals/",
      "https://nclsbayona.github.io/p/certs-real-value/",
      "https://nclsbayona.github.io/p/containers-security/",
      "https://nclsbayona.github.io/p/kubernetes-security/",
      "https://nclsbayona.github.io/p/kubernetes-architecture/",
      "https://nclsbayona.github.io/p/kubenomicon/",
      "https://nclsbayona.github.io/p/github-static-deployment-tutorial/",
      "https://nclsbayona.github.io/p/kubernetes-intro/",
      "https://nclsbayona.github.io/p/gitrepo-exec-vulnerability/",
      "https://nclsbayona.github.io/p/clustering-and-orchestration/",
      "https://nclsbayona.github.io/p/containers-intro/",
      "https://nclsbayona.github.io/p/leaky-vessels-vulnerability/",
      "https://nclsbayona.github.io/",
      "https://nclsbayona.github.io/categories/",
      "https://nclsbayona.github.io/tags/devops/",
      "https://nclsbayona.github.io/tags/devsecops/",
      "https://nclsbayona.github.io/categories/fundamentals/",
      "https://nclsbayona.github.io/categories/networking/",
      "https://nclsbayona.github.io/post/",
      "https://nclsbayona.github.io/tags/",
      "https://nclsbayona.github.io/categories/tutorials/",
      "https://nclsbayona.github.io/categories/cybersecurity/",
      "https://nclsbayona.github.io/categories/kubernetes/",
      "https://nclsbayona.github.io/tags/introductory/",
      "https://nclsbayona.github.io/categories/containers/",
      "https://nclsbayona.github.io/tags/non-technical/",
      "https://nclsbayona.github.io/categories/non-technical/",
      "https://nclsbayona.github.io/page/about/",
      "https://nclsbayona.github.io/page/archives/",
      "https://nclsbayona.github.io/page/favorites/",
      "https://nclsbayona.github.io/page/",
      "https://nclsbayona.github.io/structure/",
      "https://nclsbayona.github.io/page/search/",
      "https://nclsbayona.github.io/page/quote/"
    ]
  }
}